ipyurl/__init__.py
ipyurl/_frontend.py
ipyurl/_version.py
ipyurl/url.py
ipyurl/labextension/install.json
ipyurl/labextension/package.json
ipyurl/labextension/static/480.1446093cb19defc93321.js
ipyurl/labextension/static/480.648b204e0715953007e4.js
ipyurl/labextension/static/480.a7de25850f7af9d08bb4.js
ipyurl/labextension/static/568.a2aab510c25953333b73.js
ipyurl/labextension/static/568.c209697aa8b31d437104.js
ipyurl/labextension/static/568.dd71de67357178c19c25.js
ipyurl/labextension/static/remoteEntry.0f0a7b74e760bccda271.js
ipyurl/labextension/static/remoteEntry.607cba1a136dcce6238c.js
ipyurl/labextension/static/remoteEntry.e642945ad242e75235d8.js
ipyurl/labextension/static/style.js
ipyurl/labextension/static/third-party-licenses.json
ipyurl/nbextension/extension.js
ipyurl/nbextension/index.js
ipyurl/nbextension/index.js.LICENSE.txt
ipyurl/nbextension/index.js.map
ipyurl/tests/__init__.py
ipyurl/tests/conftest.py
ipyurl/tests/test_example.py
ipyurl/tests/test_nbextension_path.py
ipyurl-0.1.3.data/data/etc/jupyter/nbconfig/notebook.d/ipyurl.json
ipyurl-0.1.3.data/data/share/jupyter/labextensions/ipyurl/install.json
ipyurl-0.1.3.data/data/share/jupyter/labextensions/ipyurl/package.json
ipyurl-0.1.3.data/data/share/jupyter/labextensions/ipyurl/static/480.a7de25850f7af9d08bb4.js
ipyurl-0.1.3.data/data/share/jupyter/labextensions/ipyurl/static/568.c209697aa8b31d437104.js
ipyurl-0.1.3.data/data/share/jupyter/labextensions/ipyurl/static/remoteEntry.e642945ad242e75235d8.js
ipyurl-0.1.3.data/data/share/jupyter/labextensions/ipyurl/static/style.js
ipyurl-0.1.3.data/data/share/jupyter/labextensions/ipyurl/static/third-party-licenses.json
ipyurl-0.1.3.data/data/share/jupyter/nbextensions/ipyurl/extension.js
ipyurl-0.1.3.data/data/share/jupyter/nbextensions/ipyurl/index.js
ipyurl-0.1.3.data/data/share/jupyter/nbextensions/ipyurl/index.js.LICENSE.txt
ipyurl-0.1.3.data/data/share/jupyter/nbextensions/ipyurl/index.js.map
ipyurl-0.1.3.dist-info/LICENSE.txt
ipyurl-0.1.3.dist-info/METADATA
ipyurl-0.1.3.dist-info/WHEEL
ipyurl-0.1.3.dist-info/top_level.txt
ipyurl-0.1.3.dist-info/RECORD
